scyan/__init__.py
scyan/_io.py
scyan/baseline.py
scyan/data/__init__.py
scyan/data/datasets.py
scyan/data/tensors.py
scyan/model.py
scyan/module/__init__.py
scyan/module/coupling_layer.py
scyan/module/distribution.py
scyan/module/real_nvp.py
scyan/module/scyan_module.py
scyan/plot/__init__.py
scyan/plot/_scanpy_plot/README.md
scyan/plot/_scanpy_plot/__init__.py
scyan/plot/_scanpy_plot/palettes.py
scyan/plot/_scanpy_plot/plot_settings.py
scyan/plot/_scanpy_plot/umap.py
scyan/plot/density.py
scyan/plot/dot.py
scyan/plot/expressions.py
scyan/plot/graph.py
scyan/plot/heatmap.py
scyan/plot/ratios.py
scyan/plot/utils.py
scyan/preprocess.py
scyan/tools/__init__.py
scyan/tools/biomarkers.py
scyan/tools/colors.py
scyan/tools/gating.py
scyan/tools/representation.py
scyan/utils.py
scyan-1.6.2.dist-info/LICENSE
scyan-1.6.2.dist-info/METADATA
scyan-1.6.2.dist-info/WHEEL
scyan-1.6.2.dist-info/RECORD
