Metadata-Version: 2.1
Name: scyan
Version: 1.6.2
Summary: Single-cell Cytometry Annotation Network
Home-page: https://mics-lab.github.io/scyan/
License: BSD-3-Clause
Author: Blampey Quentin
Author-email: quentin.blampey@gmail.com
Requires-Python: >=3.8,<3.13
Classifier: License :: OSI Approved :: BSD License
Classifier: Operating System :: MacOS :: MacOS X
Classifier: Operating System :: Microsoft :: Windows
Classifier: Operating System :: POSIX :: Linux
Classifier: Programming Language :: Python :: 3
Classifier: Programming Language :: Python :: 3.8
Classifier: Programming Language :: Python :: 3.9
Classifier: Programming Language :: Python :: 3.10
Classifier: Programming Language :: Python :: 3.11
Classifier: Programming Language :: Python :: 3.12
Classifier: Topic :: Scientific/Engineering
Provides-Extra: dev
Provides-Extra: discovery
Provides-Extra: hydra
Requires-Dist: FlowUtils (>=1.0.0)
Requires-Dist: anndata (>=0.8.0)
Requires-Dist: black (>=22.6.0) ; extra == "dev"
Requires-Dist: fcsparser (>=0.2.4)
Requires-Dist: fcswrite (>=0.6.2)
Requires-Dist: hydra-colorlog (>=1.2.0) ; extra == "hydra"
Requires-Dist: hydra-core (>=1.2.0) ; extra == "hydra"
Requires-Dist: hydra-optuna-sweeper (>=1.2.0) ; extra == "hydra"
Requires-Dist: ipykernel (>=6.15.0) ; extra == "dev"
Requires-Dist: ipywidgets (>=7.7.1) ; extra == "dev"
Requires-Dist: isort (>=5.10.1) ; extra == "dev"
Requires-Dist: leidenalg (>=0.8.10) ; extra == "discovery"
Requires-Dist: llvmlite (>=0.38.1)
Requires-Dist: mkdocs-jupyter (>=0.21.0) ; extra == "dev"
Requires-Dist: mkdocs-material (>=8.5.0) ; extra == "dev"
Requires-Dist: mkdocstrings (>=0.19.0) ; extra == "dev"
Requires-Dist: mkdocstrings-python (>=0.7.1) ; extra == "dev"
Requires-Dist: pytest (>=7.1.2) ; extra == "dev"
Requires-Dist: pytorch-lightning (>=1.6.4)
Requires-Dist: seaborn (>=0.12.2)
Requires-Dist: torch (>=1.13)
Requires-Dist: umap-learn (>=0.5.3)
Requires-Dist: wandb (>=0.13.7) ; extra == "hydra"
Project-URL: Documentation, https://mics-lab.github.io/scyan/
Project-URL: Repository, https://github.com/MICS-Lab/scyan
